mondb
mondb/Query
mondb/urltools
