Metadata-Version: 1.0
Name: mondb
Version: 0.0.5.1
Summary: MODELS for MONGODB
Home-page: https://github.com/RevelutionWind/MDB.git
Author: plasmashadow
Author-email: plasmashadowx@gmail.com
License: BSD 2-Claus
Platform: UNKNOWN
Classifier: Programming Language :: Python
Classifier: Programming Language :: Python :: 2
Classifier: License :: OSI Approved :: GNU General Public License (GPL)
Classifier: Operating System :: OS Independent
Classifier: Development Status :: 1 - Planning
Classifier: Environment :: Console
Classifier: Intended Audience :: Science/Research
